medsegdiff/__init__.py
medsegdiff-0.0.1.dev0.dist-info/METADATA
medsegdiff-0.0.1.dev0.dist-info/WHEEL
medsegdiff-0.0.1.dev0.dist-info/top_level.txt
medsegdiff-0.0.1.dev0.dist-info/RECORD
