Metadata-Version: 2.1
Name: medsegdiff
Version: 0.0.1.dev0
Summary: medsegdiff - Medical Image Segmentation with Diffusion Probabilistic Model
Author: Shadow Walker
Keywords: med-seg-diff
Classifier: Programming Language :: Python :: 3
Classifier: Programming Language :: Python :: 3.8
Classifier: Programming Language :: Python :: 3.9
Classifier: Programming Language :: Python :: 3.10
Requires-Dist: torch
